wikiphilosophy/__init__.py
wikiphilosophy-0.3.3.dist-info/DESCRIPTION.rst
wikiphilosophy-0.3.3.dist-info/METADATA
wikiphilosophy-0.3.3.dist-info/RECORD
wikiphilosophy-0.3.3.dist-info/WHEEL
wikiphilosophy-0.3.3.dist-info/entry_points.txt
wikiphilosophy-0.3.3.dist-info/metadata.json
wikiphilosophy-0.3.3.dist-info/top_level.txt
