Metadata-Version: 2.0
Name: wikiphilosophy
Version: 0.3.3
Summary: See how every wikipedia article leads to Philosophy
Home-page: UNKNOWN
Author: Adhityaa Chandrasekar
Author-email: c.adhityaa@gmail.com
License: AGPL-3.0
Platform: any
Classifier: Development Status :: 4 - Beta
Classifier: Environment :: Console
Classifier: Environment :: MacOS X
Classifier: Environment :: Win32 (MS Windows)
Classifier: Environment :: X11 Applications :: Gnome
Classifier: Intended Audience :: Developers
Classifier: License :: OSI Approved :: GNU Affero General Public License v3 or later (AGPLv3+)
Classifier: Operating System :: OS Independent
Classifier: Programming Language :: Python :: Implementation :: CPython
Classifier: Programming Language :: Python :: 3.4
Classifier: Programming Language :: Python :: 3.5
Classifier: Programming Language :: Python :: 3 :: Only
Requires-Dist: beautifulsoup4 (==4.5.1)
Requires-Dist: wikipedia (==1.4.0)
